TODO.txt
setup.py
OpenCorePaste.egg-info/PKG-INFO
OpenCorePaste.egg-info/SOURCES.txt
OpenCorePaste.egg-info/dependency_links.txt
OpenCorePaste.egg-info/entry_points.txt
OpenCorePaste.egg-info/not-zip-safe
OpenCorePaste.egg-info/requires.txt
OpenCorePaste.egg-info/top_level.txt
opencorepaste/__init__.py
opencorepaste/paster-templates/opencore_plugin/setup.py_tmpl
opencorepaste/paster-templates/opencore_plugin/+package+/__init__.py
opencorepaste/paster-templates/opencore_plugin/+package+/configure.zcml