Metadata-Version: 1.0
Name: OpenCorePaste
Version: 0.1
Summary: pastescript template for opencore plugin authors
Home-page: UNKNOWN
Author: Ethan Jucovy
Author-email: opencore-dev@lists.coactivate.org
License: GPLv3
Platform: UNKNOWN
